{
  "indexes": [
    {
      "collectionGroup": "sessionsMontageAtelier",
      "queryScope": "COLLECTION",
      "fields": [
        { "fieldPath": "monteurIds", "arrayConfig": "CONTAINS" },
        { "fieldPath": "date", "order": "ASCENDING" }
      ]
    },
    {
      "collectionGroup": "paiementsEquipe",
      "queryScope": "COLLECTION",
      "fields": [
        { "fieldPath": "memberId", "order": "ASCENDING" },
        { "fieldPath": "date", "order": "ASCENDING" }
      ]
    }
  ],
  "fieldOverrides": []
}
